[
  {
    "categoria": "[COLORwhite]ENTRAR[/COLOR]",
    "icon": "https://i.imgur.com/FBK5qFX.png",
    "fanart": "https://i.imgur.com/KMlkWXm.jpeg",
    "servidores": [
      {
        "nome": "[COLORwhite]Servidor 1[/COLOR]",
        "dns": "http://aguacomgas.shop",
        "username": "SuelenLeal1",
        "password": "3yrpc3",
        "icon": "https://i.imgur.com/FBK5qFX.png"
      },
      {
        "nome": "[COLORwhite]Servidor 2[/COLOR]",
        "dns": "http://dnsit.click:80",
        "username": "rebeccareis729",
        "password": "9746736889",
        "icon": "https://i.imgur.com/FBK5qFX.png"
      },
      {
        "nome": "[COLORwhite]Servidor 3[/COLOR]",
        "dns": "http://bananadoce.online:80",
        "username": "EudesBR",
        "password": "63133441194",
        "icon": "https://i.imgur.com/FBK5qFX.png"
      },
      {
        "nome": "[COLORwhite]Servidor 4[/COLOR]",
        "dns": "http://huloftibu.lol:80",
        "username": "598319998",
        "password": "896685131",
        "icon": "https://i.imgur.com/FBK5qFX.png"
      },
      {
        "nome": "[COLORwhite]Servidor 5[/COLOR]",
        "dns": "http://rtdkh.xyz",
        "username": "052852926",
        "password": "893075088",
        "icon": "https://i.imgur.com/FBK5qFX.png"
      },
      {
        "nome": "[COLORwhite]Servidor 6[/COLOR]",
        "dns": "http://rtdkh.xyz",
        "username": "2MATHPAVI",
        "password": "002000200",
        "icon": "https://i.imgur.com/FBK5qFX.png"
      }
    ]
  }
]
